sdcopy/__init__.py
sdcopy/__main__.py
sdcopy/cli.py
sdcopy/tests/__init__.py
sdcopy/tests/test_cli.py
sdcopy-0.3.0.dist-info/LICENSE
sdcopy-0.3.0.dist-info/METADATA
sdcopy-0.3.0.dist-info/WHEEL
sdcopy-0.3.0.dist-info/entry_points.txt
sdcopy-0.3.0.dist-info/RECORD
