Metadata-Version: 2.3
Name: sdcopy
Version: 0.3.0
Summary: Tool for saving files off SD cards
License: MIT
Author: Dmitry Gerasimenko
Author-email: kiddima@gmail.com
Requires-Python: >=3.11,<4.0
Classifier: Development Status :: 4 - Beta
Classifier: Environment :: Console
Classifier: License :: OSI Approved :: MIT License
Classifier: Natural Language :: English
Classifier: Programming Language :: Python
Classifier: Programming Language :: Python :: 3
Classifier: Programming Language :: Python :: 3.11
Classifier: Programming Language :: Python :: 3.12
Classifier: Programming Language :: Python :: 3.13
Classifier: Topic :: Multimedia
Classifier: Topic :: Multimedia :: Graphics
Classifier: Topic :: Multimedia :: Video
Classifier: Topic :: Utilities
Project-URL: Repository, https://github.com/kidig/sdcopy
